blend360_all_star_clickstream_api/__init__.py
blend360_all_star_clickstream_api/datafetch.py
blend360_all_star_clickstream_api-0.1.2.dist-info/LICENSE
blend360_all_star_clickstream_api-0.1.2.dist-info/METADATA
blend360_all_star_clickstream_api-0.1.2.dist-info/WHEEL
blend360_all_star_clickstream_api-0.1.2.dist-info/top_level.txt
blend360_all_star_clickstream_api-0.1.2.dist-info/RECORD
