Metadata-Version: 2.1
Name: blend360-all-star-clickstream-api
Version: 0.1.2
Summary: Package to request synthetic clickstream data.
Author: Blend360
Requires-Python: >=3.9
License-File: LICENSE
Requires-Dist: setuptools
Requires-Dist: requests
Requires-Dist: keyring
